[{
  "_id": {
    "$oid": "6602fe7c3904b9b4b704d5f2"
  },
  "name": [
    "chân gà rút xương",
    "mỳ ramen",
    "tỏi",
    "gừng",
    "tỏi tây",
    "nước luộc gà",
    "tảo kombu",
    "nước sốt đậu lành",
    "sake",
    "mirin",
    "trứng",
    "hành lá",
    "mầm đậu nành"
  ],
  "quantity": [
    4,
    200,
    6,
    60,
    1,
    2,
    1,
    125,
    50,
    50,
    2,
    1,
    20
  ],
  "unit": [
    "cái",
    "g",
    "tép",
    "g",
    "củ",
    "l",
    "miếng",
    "ml",
    "ml",
    "ml",
    "quả",
    "củ",
    "g"
  ],
  "price": [
    10,
    10,
    10,
    10,
    10,
    10,
    10,
    10,
    10,
    10,
    10,
    10,
    10
  ],
  "createdAt": {
    "$date": "2024-03-26T16:57:32.027Z"
  },
  "updatedAt": {
    "$date": "2024-03-26T16:57:32.027Z"
  },
  "__v": 0
},
{
  "_id": {
    "$oid": "66037b027f9728bdfe595af0"
  },
  "name": [
    "đậu khô xanh",
    "bột nở",
    "củ hành",
    "tỏi",
    "ớt",
    "mùi tây",
    "ngò",
    "thì là xay",
    "rau mùi đất",
    "hạt mè",
    "cây bạc hà",
    "Greek yougurt"
  ],
  "quantity": [
    400,
    "½",
    1,
    3,
    "½",
    40,
    20,
    1,
    1,
    2,
    10,
    200
  ],
  "unit": [
    "g",
    "tsp",
    "củ",
    "tép",
    "",
    "g",
    "g",
    "tsp",
    "tsp",
    "tbsp",
    "g",
    "g"
  ],
  "price": [
    10,
    10,
    10,
    10,
    10,
    10,
    10,
    10,
    10,
    10,
    10,
    10
  ],
  "createdAt": {
    "$date": "2024-03-27T01:48:50.300Z"
  },
  "updatedAt": {
    "$date": "2024-03-27T01:48:50.300Z"
  },
  "__v": 0
},
{
  "_id": {
    "$oid": "6603819d56bf36d35832fe4f"
  },
  "name": [
    "cà tím",
    "quả bí",
    "ớt chuông vàng",
    "cà chua",
    "hành đỏ",
    "tỏi",
    "lá kinh giới",
    "rau kinh giới",
    "hương thảo",
    "xạ hương",
    "dầu ô liu",
    "bột cà chua",
    "lá nguyệt quế",
    "giấm balsamic"
  ],
  "quantity": [
    350,
    200,
    200,
    300,
    1,
    2,
    5,
    5,
    5,
    5,
    4,
    2,
    2,
    2
  ],
  "unit": [
    "g",
    "g",
    "g",
    "g",
    "củ",
    "tép",
    "g",
    "g",
    "g",
    "g",
    "tbsp",
    "tbsp",
    "lá",
    "tbsp"
  ],
  "price": [
    10,
    10,
    10,
    10,
    10,
    10,
    10,
    10,
    10,
    10,
    10,
    10,
    10,
    10
  ],
  "createdAt": {
    "$date": "2024-03-27T02:17:01.619Z"
  },
  "updatedAt": {
    "$date": "2024-03-27T02:17:01.619Z"
  },
  "__v": 0
},
{
  "_id": {
    "$oid": "6603a16bfa8240f7beef9848"
  },
  "name": [
    "ức gà",
    "hạt mè trắng",
    "hạt mè đen",
    "gạo",
    "cải thìa trắng",
    "tỏi",
    "ớt",
    "tinh bột",
    "muối",
    "nước cốt dừa",
    "xì dầu",
    "bơ đậu phộng"
  ],
  "quantity": [
    2,
    4,
    2,
    150,
    2,
    1,
    1,
    1,
    "⅛",
    200,
    2,
    50
  ],
  "unit": [
    "miếng",
    "tbsp",
    "tbsp",
    "g",
    "cây",
    "tép",
    "quả",
    "tbsp",
    "tsp",
    "ml",
    "tbsp",
    "g"
  ],
  "price": [
    10,
    10,
    10,
    10,
    10,
    10,
    10,
    10,
    10,
    10,
    10,
    10
  ],
  "createdAt": {
    "$date": "2024-03-27T04:32:43.424Z"
  },
  "updatedAt": {
    "$date": "2024-03-27T04:32:43.424Z"
  },
  "__v": 0
},
{
  "_id": {
    "$oid": "6603ea3fa69c95c19cf26cdd"
  },
  "name": [
    "cơm",
    "trứng",
    "đậu Hà Lan",
    "măng tây xanh",
    "cà rốt",
    "hành lá",
    "xì dầu"
  ],
  "quantity": [
    200,
    3,
    100,
    4,
    1,
    2,
    1
  ],
  "unit": [
    "g",
    "quả",
    "g",
    "cây",
    "củ",
    "cây",
    "tsp"
  ],
  "price": [
    10,
    10,
    10,
    10,
    10,
    10,
    10
  ],
  "createdAt": {
    "$date": "2024-03-27T09:43:27.783Z"
  },
  "updatedAt": {
    "$date": "2024-03-27T09:43:27.783Z"
  },
  "__v": 0
},
{
  "_id": {
    "$oid": "6603f2831e9f2ad666ecb9eb"
  },
  "name": [
    "Thịt băm chay",
    "xả",
    "bún",
    "tỏi",
    "gừng",
    "nước tương ngọt",
    "xì dầu nhạt",
    "đường",
    "chanh",
    "hành lá",
    "cà rốt",
    "dưa chuột",
    "bắp cải",
    "cà chua",
    "ớt Thái",
    "đậu phộng rang",
    "húng quế",
    "bạc hà"
  ],
  "quantity": [
    200,
    3,
    100,
    3,
    10,
    1,
    1,
    3,
    3,
    1,
    1,
    "½",
    "¼",
    150,
    1,
    50,
    20,
    20
  ],
  "unit": [
    "g",
    "cây",
    "g",
    "tép",
    "g",
    "tbsp",
    "tbsp",
    "tsp",
    "quả",
    "cây",
    "củ",
    "quả",
    "cái",
    "g",
    "quả",
    "g",
    "g",
    "g"
  ],
  "price": [
    10,
    10,
    10,
    10,
    10,
    10,
    10,
    10,
    10,
    10,
    10,
    10,
    10,
    10,
    10,
    10,
    10,
    10
  ],
  "createdAt": {
    "$date": "2024-03-27T10:18:43.589Z"
  },
  "updatedAt": {
    "$date": "2024-03-27T10:18:43.589Z"
  },
  "__v": 0
},
{
  "_id": {
    "$oid": "6604eda1216e2cb1a066eefc"
  },
  "name": [
    "thịt heo xay",
    "giấy gói hoành thánh (đông lạnh)",
    "hành lá",
    "gừng",
    "tỏi",
    "trứng",
    "nước tương",
    "rượu",
    "dầu hào",
    "dầu mè nướng",
    "tiêu trắng",
    "ớt",
    "nước tương nhạt",
    "bột tiêu Tứ Xuyên"
  ],
  "quantity": [
    300,
    35,
    3,
    2,
    4,
    1,
    2,
    1,
    2,
    1,
    "¼",
    4,
    4,
    1
  ],
  "unit": [
    "g",
    "",
    "cây",
    "tbsp",
    "tép",
    "quả",
    "tbsp",
    "tbsp",
    "tbsp",
    "tbsp",
    "tsp",
    "tbsp",
    "tbsp",
    "tsp"
  ],
  "price": [
    10,
    10,
    10,
    10,
    10,
    10,
    10,
    10,
    10,
    10,
    10,
    10,
    10,
    10
  ],
  "createdAt": {
    "$date": "2024-03-28T04:10:09.331Z"
  },
  "updatedAt": {
    "$date": "2024-03-28T04:10:09.331Z"
  },
  "__v": 0
},
{
  "_id": {
    "$oid": "6605863558f2e256c6ef9f98"
  },
  "name": [
    "súp lơ",
    "ức gà",
    "hương thảo",
    "tinh bột",
    "cà rốt",
    "tỏi",
    "hành củ",
    "hành lá",
    "hạt thông",
    "đậu hà lan"
  ],
  "quantity": [
    500,
    300,
    "1⅓",
    1,
    1,
    1,
    1,
    2,
    20,
    100
  ],
  "unit": [
    "g",
    "g",
    "tbsp",
    "tsp",
    "củ",
    "tép",
    "củ",
    "cây",
    "g",
    "g"
  ],
  "price": [
    10,
    10,
    10,
    10,
    10,
    10,
    10,
    10,
    10,
    10
  ],
  "createdAt": {
    "$date": "2024-03-28T15:01:09.564Z"
  },
  "updatedAt": {
    "$date": "2024-03-28T15:01:09.564Z"
  },
  "__v": 0
},
{
  "_id": {
    "$oid": "6605a3ca84906b0c3a8cfed3"
  },
  "name": [
    "bột ngô polenta",
    "đậu hà lan",
    "bông cải xanh",
    "măng tây xanh",
    "phô mai Parmesan",
    "bơ không muối",
    "dầu oliu",
    "rau thì là",
    "mùi tây"
  ],
  "quantity": [
    150,
    90,
    150,
    150,
    60,
    2,
    1,
    1,
    1
  ],
  "unit": [
    "g",
    "g",
    "g",
    "g",
    "g",
    "tbsp",
    "tbsp",
    "tsp",
    "tsp"
  ],
  "price": [
    10,
    10,
    10,
    10,
    10,
    10,
    10,
    10,
    10
  ],
  "createdAt": {
    "$date": "2024-03-28T17:07:22.222Z"
  },
  "updatedAt": {
    "$date": "2024-03-28T17:07:22.222Z"
  },
  "__v": 0
},
{
  "_id": {
    "$oid": "6606356ba544942651840deb"
  },
  "name": [
    "bột mì",
    "bột nở",
    "đường",
    "muối",
    "trứng",
    "sữa",
    "bơ không muối"
  ],
  "quantity": [
    270,
    2,
    2,
    1,
    2,
    320,
    2
  ],
  "unit": [
    "g",
    "tsb",
    "tbsp",
    "tsb",
    "quả",
    "ml",
    "tbsp"
  ],
  "price": [
    10,
    10,
    10,
    10,
    10,
    10,
    10
  ],
  "createdAt": {
    "$date": "2024-03-29T03:28:43.173Z"
  },
  "updatedAt": {
    "$date": "2024-03-29T03:28:43.173Z"
  },
  "__v": 0
},
{
  "_id": {
    "$oid": "6606760f8ab99dfe9f153444"
  },
  "name": [
    "miến",
    "dưa chuột",
    "cà rốt",
    "ớt chuông vàng",
    "xoài",
    "đậu tuyết",
    "chanh",
    "ớt",
    "xả",
    "dầu mè",
    "nước tương",
    "giấm gạo",
    "rau bạc à",
    "ngò"
  ],
  "quantity": [
    250,
    1,
    1,
    1,
    1,
    150,
    2,
    1,
    1,
    2,
    2,
    2,
    10,
    10
  ],
  "unit": [
    "g",
    "quả",
    "củ",
    "quả",
    "quả",
    "g",
    "quả",
    "quả",
    "cây",
    "tsp",
    "tbsp",
    "tsp",
    "g",
    "g"
  ],
  "price": [
    10,
    10,
    10,
    10,
    10,
    10,
    10,
    10,
    10,
    10,
    10,
    10,
    10,
    10
  ],
  "createdAt": {
    "$date": "2024-03-29T08:04:31.641Z"
  },
  "updatedAt": {
    "$date": "2024-03-29T08:04:31.641Z"
  },
  "__v": 0
},
{
  "_id": {
    "$oid": "6606798934289c6b3f0a6257"
  },
  "name": [
    "đậu hũ non",
    "dầu đậu phộng",
    "cà chua",
    "hành lá",
    "tỏi",
    "hương thảo",
    "giấm",
    "Sriracha"
  ],
  "quantity": [
    400,
    3,
    500,
    2,
    2,
    4,
    1,
    2
  ],
  "unit": [
    "g",
    "tbsp",
    "g",
    "cây",
    "tép",
    "tbsp",
    "tbsp",
    "tsp"
  ],
  "price": [
    10,
    10,
    10,
    10,
    10,
    10,
    10,
    10
  ],
  "createdAt": {
    "$date": "2024-03-29T08:19:21.536Z"
  },
  "updatedAt": {
    "$date": "2024-03-29T08:19:21.536Z"
  },
  "__v": 0
},
{
  "_id": {
    "$oid": "660699cbb93eedaea57a3e3b"
  },
  "name": [
    "đuôi bò",
    "xương bò",
    "thịt bò",
    "thăn bò",
    "bánh phở",
    "hẹ tây",
    "gừng",
    "vỏ thảo quả",
    "hạt thì là",
    "thanh quế",
    "hoa hồi",
    "hành lá",
    "ớt",
    "giá đỗ",
    "rau bạc hà",
    "ngò"
  ],
  "quantity": [
    500,
    500,
    500,
    200,
    250,
    5,
    40,
    1,
    1,
    1,
    1,
    5,
    2,
    20,
    4,
    4
  ],
  "unit": [
    "g",
    "g",
    "g",
    "g",
    "g",
    "",
    "g",
    "",
    "tsp",
    "",
    "",
    "",
    "",
    "g",
    "nhánh",
    "nhánh"
  ],
  "price": [
    10,
    10,
    10,
    10,
    10,
    10,
    10,
    10,
    10,
    10,
    10,
    10,
    10,
    10,
    10,
    10
  ],
  "createdAt": {
    "$date": "2024-03-29T10:36:59.181Z"
  },
  "updatedAt": {
    "$date": "2024-03-29T10:36:59.181Z"
  },
  "__v": 0
},
{
  "_id": {
    "$oid": "6606f567a6e3f1773b1bfd0c"
  },
  "name": [
    "đùi gà",
    "dưa chuột",
    "rượu",
    "tiêu",
    "gừng xay",
    "giấm",
    "đường nâu",
    "hành lá",
    "ớt",
    "ngò",
    "tinh bột",
    "tỏi",
    "sốt cà chua",
    "Gochujang",
    "mật ong",
    "nước tương",
    "dầu mè",
    "đậu phộng"
  ],
  "quantity": [
    600,
    1,
    1,
    "½",
    2,
    2,
    "3½",
    2,
    1,
    10,
    2,
    1,
    5,
    2,
    2,
    2,
    2,
    2
  ],
  "unit": [
    "g",
    "quả",
    "tbsp",
    "tsp",
    "tsp",
    "tbsp",
    "tbsp",
    "nhánh",
    "quả",
    "g",
    "tbsp",
    "tép",
    "tbsp",
    "tbsp",
    "tbsp",
    "tbsp",
    "tbsp",
    "tbsp"
  ],
  "price": [
    10,
    10,
    10,
    10,
    10,
    10,
    10,
    10,
    10,
    10,
    10,
    10,
    10,
    10,
    10,
    10,
    10,
    10
  ],
  "createdAt": {
    "$date": "2024-03-29T17:07:51.931Z"
  },
  "updatedAt": {
    "$date": "2024-03-29T17:07:51.931Z"
  },
  "__v": 0
},
{
  "_id": {
    "$oid": "6617a4744d970e4db615c919"
  },
  "name": [
    "cà rốt",
    "húng quế",
    "ngò",
    "rau bạc hà",
    "đậu phụ",
    "ớt chuông",
    "hành lá",
    "rau riếp",
    "đậu phộng",
    "giấy gói gạo",
    "hạt vừng",
    "sốt đậu phộng"
  ],
  "quantity": [
    1,
    10,
    10,
    10,
    200,
    1,
    3,
    1,
    60,
    10,
    60,
    200
  ],
  "unit": [
    "củ",
    "g",
    "g",
    "g",
    "g",
    "quả",
    "cọng",
    "cây",
    "g",
    "",
    "g",
    "ml"
  ],
  "price": [
    10,
    10,
    10,
    10,
    10,
    10,
    10,
    10,
    10,
    10,
    10,
    10
  ],
  "createdAt": {
    "$date": "2024-04-11T08:51:00.418Z"
  },
  "updatedAt": {
    "$date": "2024-04-11T08:51:00.418Z"
  },
  "__v": 0
},
{
  "_id": {
    "$oid": "6617a8529fef544640cb5a55"
  },
  "name": [
    "Bánh mì",
    "xúc xích",
    "rau mùi",
    "tương ớt",
    "giò lụa",
    "mayonaise",
    "phô mai"
  ],
  "quantity": [
    2,
    100,
    15,
    10,
    100,
    15,
    1
  ],
  "unit": [
    "cái",
    "g",
    "g",
    "ml",
    "g",
    "ml",
    "miếng"
  ],
  "price": [
    5,
    5,
    5,
    5,
    5,
    5,
    5
  ],
  "createdAt": {
    "$date": "2024-04-11T09:07:30.556Z"
  },
  "updatedAt": {
    "$date": "2024-04-11T09:07:30.556Z"
  },
  "__v": 0
},
{
  "_id": {
    "$oid": "6617ab8a5b6774dfc0b693a9"
  },
  "name": [
    "nước xương hầm",
    "thịt bò hầm",
    "thăn bò",
    "bánh phở",
    "cà rốt",
    "tỏi",
    "gừng",
    "hành lá",
    "hạt thì là",
    "ớt",
    "nước mắm",
    "ngò"
  ],
  "quantity": [
    2,
    400,
    300,
    150,
    1,
    2,
    2,
    3,
    1,
    2,
    50,
    10
  ],
  "unit": [
    "l",
    "g",
    "g",
    "g",
    "củ",
    "tép",
    "nhánh",
    "cọng",
    "tbsp",
    "quả",
    "ml",
    "g"
  ],
  "price": [
    10,
    10,
    10,
    10,
    10,
    10,
    10,
    10,
    10,
    10,
    10,
    10
  ],
  "createdAt": {
    "$date": "2024-04-11T09:21:14.456Z"
  },
  "updatedAt": {
    "$date": "2024-04-11T09:21:14.456Z"
  },
  "__v": 0
},
{
  "_id": {
    "$oid": "6617af41190064930d74fa10"
  },
  "name": [
    "chuối chín",
    "bơ",
    "đường",
    "trứng",
    "sữa",
    "quế",
    "bột mì",
    "bột nở",
    "baking soda",
    "muối",
    "đường nâu"
  ],
  "quantity": [
    4,
    120,
    150,
    2,
    1,
    1,
    250,
    1,
    1,
    1,
    1
  ],
  "unit": [
    "quả",
    "g",
    "g",
    "quả",
    "tbsp",
    "tsp",
    "g",
    "tsp",
    "tsp",
    "tsp",
    "tbsp"
  ],
  "price": [
    10,
    10,
    10,
    10,
    10,
    10,
    10,
    10,
    10,
    10,
    10
  ],
  "createdAt": {
    "$date": "2024-04-11T09:37:05.766Z"
  },
  "updatedAt": {
    "$date": "2024-04-11T09:37:05.766Z"
  },
  "__v": 0
},
{
  "_id": {
    "$oid": "6617b22fc5badc20ddefcc06"
  },
  "name": [
    "nước chanh",
    "vỏ chanh",
    "bơ",
    "đường caster",
    "vani",
    "muối",
    "trứng",
    "rich",
    "bột mì",
    "bột nở",
    "đường bánh kẹo"
  ],
  "quantity": [
    8,
    3,
    170,
    250,
    1,
    "¼",
    3,
    160,
    280,
    3,
    350
  ],
  "unit": [
    "tbsp",
    "tsp",
    "g",
    "g",
    "tsp",
    "tsp",
    "quả",
    "g",
    "g",
    "tsp",
    "g"
  ],
  "price": [
    10,
    10,
    10,
    10,
    10,
    10,
    10,
    10,
    10,
    10,
    10
  ],
  "createdAt": {
    "$date": "2024-04-11T09:49:35.134Z"
  },
  "updatedAt": {
    "$date": "2024-04-11T09:49:35.134Z"
  },
  "__v": 0
},
{
  "_id": {
    "$oid": "6617f766250161b103bbe1f0"
  },
  "name": [
    "bột mì",
    "bơ",
    "baking soda",
    "muối",
    "đường",
    "đường nâu",
    "trứng",
    "vani",
    "sô cô la sữa",
    "trứng sô cô la mini"
  ],
  "quantity": [
    150,
    100,
    "¼",
    "¼",
    60,
    60,
    1,
    2,
    100,
    150
  ],
  "unit": [
    "g",
    "g",
    "tsp",
    "tsp",
    "g",
    "g",
    "quả",
    "tbsp",
    "g",
    "g"
  ],
  "price": [
    10,
    10,
    10,
    10,
    10,
    10,
    10,
    10,
    10,
    10
  ],
  "createdAt": {
    "$date": "2024-04-11T14:44:54.732Z"
  },
  "updatedAt": {
    "$date": "2024-04-11T14:44:54.732Z"
  },
  "__v": 0
},
{
  "_id": {
    "$oid": "6618818b09cd5828f8b07e1c"
  },
  "name": [
    "kem phô mai",
    "đường",
    "trứng",
    "kem nặng",
    "vani",
    "muối",
    "bột mì"
  ],
  "quantity": [
    900,
    300,
    6,
    470,
    1,
    "½",
    50
  ],
  "unit": [
    "g",
    "g",
    "quả",
    "g",
    "tbsp",
    "tsp",
    "g"
  ],
  "price": [
    10,
    10,
    10,
    10,
    10,
    10,
    10
  ],
  "createdAt": {
    "$date": "2024-04-12T00:34:19.741Z"
  },
  "updatedAt": {
    "$date": "2024-04-12T00:34:19.741Z"
  },
  "__v": 0
},
{
  "_id": {
    "$oid": "6618e93647d143505fa61ba5"
  },
  "name": [
    "bún khô",
    "thị bò",
    "ớt chuông (đỏ)",
    "hành tây",
    "bạc hà",
    "nước tương",
    "mật ong",
    "nước mắm",
    "tương ớt ngọt",
    "chanh",
    "dầu đậu phộng",
    "đậu phộng"
  ],
  "quantity": [
    150,
    300,
    1,
    1,
    10,
    40,
    1,
    20,
    20,
    "½",
    "½",
    50
  ],
  "unit": [
    "g",
    "g",
    "quả",
    "củ",
    "g",
    "ml",
    "tsp",
    "ml",
    "ml",
    "",
    "tbsp",
    "g"
  ],
  "price": [
    10,
    10,
    10,
    10,
    10,
    10,
    10,
    10,
    10,
    10,
    10,
    10
  ],
  "createdAt": {
    "$date": "2024-04-12T07:56:38.109Z"
  },
  "updatedAt": {
    "$date": "2024-04-12T07:56:38.109Z"
  },
  "__v": 0
},
{
  "_id": {
    "$oid": "6618ee75b0b210f4e3b5f1e6"
  },
  "name": [
    "mì trứng",
    "cà rốt",
    "đậu xanh",
    "đậu tuyết",
    "ớt chuông đỏ",
    "hành lá",
    "ớt",
    "giấm",
    "nước tương",
    "đậu phộng rang muối",
    "dầu mè nướng",
    "hạt mè đen"
  ],
  "quantity": [
    200,
    1,
    80,
    80,
    "½",
    2,
    1,
    1,
    2,
    50,
    3,
    1
  ],
  "unit": [
    "g",
    "củ",
    "g",
    "g",
    "quả",
    "cọng",
    "quả",
    "tbsp",
    "tbsp",
    "g",
    "tbsp",
    "tbsp"
  ],
  "price": [
    10,
    10,
    10,
    10,
    10,
    10,
    10,
    10,
    10,
    10,
    10,
    10
  ],
  "createdAt": {
    "$date": "2024-04-12T08:19:01.260Z"
  },
  "updatedAt": {
    "$date": "2024-04-12T08:19:01.260Z"
  },
  "__v": 0
},
{
  "_id": {
    "$oid": "661a46a35dfb2cbdc4e8588b"
  },
  "name": [
    "khoai tây",
    "cà chua",
    "gừng",
    "tỏi",
    "ớt xanh",
    "hạt thì là đen",
    "rau mùi đất",
    "Garam Masala",
    "bơ"
  ],
  "quantity": [
    500,
    2,
    15,
    1,
    1,
    1,
    1,
    1,
    1
  ],
  "unit": [
    "g",
    "quả",
    "g",
    "tép",
    "quả",
    "tsp",
    "tsp",
    "tsp",
    "tsp"
  ],
  "price": [
    10,
    10,
    10,
    10,
    10,
    10,
    10,
    10,
    10
  ],
  "createdAt": {
    "$date": "2024-04-13T08:47:31.887Z"
  },
  "updatedAt": {
    "$date": "2024-04-13T08:47:31.887Z"
  },
  "__v": 0
},
{
  "_id": {
    "$oid": "661e4024cc89d74c57316a3f"
  },
  "name": [
    "nhân đậu đen Hàn Quốc",
    "mì tươi",
    "bì lợn",
    "Zucchini",
    "bắp cải trắng",
    "hành",
    "dưa chuột",
    "gừng",
    "tinh bột",
    "đường"
  ],
  "quantity": [
    5,
    450,
    250,
    1,
    100,
    1,
    "½",
    15,
    1,
    1
  ],
  "unit": [
    "tbsp",
    "g",
    "g",
    "",
    "g",
    "",
    "",
    "g",
    "tbsp",
    "tsp"
  ],
  "price": [
    10,
    10,
    10,
    10,
    10,
    10,
    10,
    10,
    10,
    10
  ],
  "createdAt": {
    "$date": "2024-04-16T09:08:52.234Z"
  },
  "updatedAt": {
    "$date": "2024-04-16T09:08:52.234Z"
  },
  "__v": 0
},
{
  "_id": {
    "$oid": "661e43b0b098dd7d867e7305"
  },
  "name": [
    "thịt bò",
    "gừng",
    "tỏi",
    "hành",
    "dầu mè",
    "sake",
    "nước ép lê",
    "miso dán",
    "Gochujang",
    "hành lá"
  ],
  "quantity": [
    300,
    5,
    1,
    1,
    20,
    30,
    150,
    1,
    1,
    2
  ],
  "unit": [
    "g",
    "g",
    "tép",
    "",
    "ml",
    "ml",
    "ml",
    "tbsp",
    "tbsp",
    ""
  ],
  "price": [
    10,
    10,
    10,
    10,
    10,
    10,
    10,
    10,
    10,
    10
  ],
  "createdAt": {
    "$date": "2024-04-16T09:24:00.595Z"
  },
  "updatedAt": {
    "$date": "2024-04-16T09:24:00.595Z"
  },
  "__v": 0
},
{
  "_id": {
    "$oid": "661e8dd7d221aa4d31acdbfa"
  },
  "name": [
    "hành",
    "cà rốt",
    "ớt chuông",
    "nấm nút",
    "hành lá",
    "tỏi",
    "gừng",
    "miến",
    "dầu mè nướng",
    "nước tương",
    "mè"
  ],
  "quantity": [
    1,
    1,
    1,
    250,
    2,
    1,
    10,
    170,
    2,
    2,
    1
  ],
  "unit": [
    "củ",
    "củ",
    "quả",
    "g",
    "",
    "tép",
    "g",
    "g",
    "tbsp",
    "tbsp",
    "tbsp"
  ],
  "price": [
    10,
    10,
    10,
    10,
    10,
    10,
    10,
    10,
    10,
    10,
    10
  ],
  "createdAt": {
    "$date": "2024-04-16T14:40:23.848Z"
  },
  "updatedAt": {
    "$date": "2024-04-16T14:40:23.848Z"
  },
  "__v": 0
},
{
  "_id": {
    "$oid": "66214c602f14766224468dc9"
  },
  "name": [
    "thịt bò xay",
    "hành tím",
    "rau diếp",
    "dưa chua",
    "mayonnaise",
    "tương cà",
    "mù tạt",
    "bánh burger",
    "phô mai"
  ],
  "quantity": [
    500,
    1,
    1,
    20,
    3,
    1,
    1,
    4,
    4
  ],
  "unit": [
    "g",
    "củ",
    "cây",
    "g",
    "tbsp",
    "tbsp",
    "tbsp",
    "",
    "miếng"
  ],
  "price": [
    10,
    10,
    10,
    10,
    10,
    10,
    10,
    10,
    10
  ],
  "createdAt": {
    "$date": "2024-04-18T16:37:52.027Z"
  },
  "updatedAt": {
    "$date": "2024-04-18T16:37:52.027Z"
  },
  "__v": 0
}]